MANIFEST.in
README.md
build.py
requirements-dev.txt
requirements.txt
setup.py
crypto_screening/dataset.py
crypto_screening/exchanges.py
crypto_screening/symbols.py
crypto_screening/validate.py
crypto_screening.egg-info/PKG-INFO
crypto_screening.egg-info/SOURCES.txt
crypto_screening.egg-info/dependency_links.txt
crypto_screening.egg-info/requires.txt
crypto_screening.egg-info/top_level.txt
crypto_screening/collect/assets.py
crypto_screening/collect/screeners.py
crypto_screening/collect/symbols.py
crypto_screening/collect/foundation/exchanges.py
crypto_screening/collect/market/dynamic.py
crypto_screening/collect/market/ohlcv.py
crypto_screening/collect/market/orderbook.py
crypto_screening/collect/market/tickers.py
crypto_screening/collect/market/trades.py
crypto_screening/collect/market/state/__init__.py
crypto_screening/collect/market/state/assets.py
crypto_screening/collect/market/state/base.py
crypto_screening/collect/market/state/symbols.py
crypto_screening/foundation/container.py
crypto_screening/foundation/data.py
crypto_screening/foundation/market.py
crypto_screening/foundation/protocols.py
crypto_screening/foundation/screener.py
crypto_screening/foundation/state.py
crypto_screening/foundation/waiting.py
crypto_screening/screeners/__init__.py
crypto_screening/screeners/base.py
crypto_screening/screeners/combined.py
crypto_screening/screeners/container.py
crypto_screening/screeners/database.py
crypto_screening/screeners/market.py
crypto_screening/screeners/ohlcv.py
crypto_screening/screeners/orderbook.py
crypto_screening/screeners/recorder.py
crypto_screening/screeners/screener.py
crypto_screening/screeners/tickers.py
crypto_screening/screeners/trades.py
crypto_screening/screeners/waiting.py
crypto_screening/screeners/callbacks/__init__.py
crypto_screening/screeners/callbacks/base.py
crypto_screening/screeners/callbacks/database.py
crypto_screening/screeners/callbacks/sockets.py
crypto_screening/screeners/collectors/__init__.py
crypto_screening/screeners/collectors/base.py
crypto_screening/screeners/collectors/database.py
crypto_screening/screeners/collectors/sockets.py
crypto_screening/screeners/orchestration/__init__.py
